{
  "type": "FeatureCollection",
  "features": [
    {
      "type": "Feature",
      "geometry": {
        "type": "Polygon",
        "coordinates": [
          [
            [-119.790028, 39.533832],
            [-119.789983, 39.533832],
            [-119.789985, 39.534208],
            [-119.789141, 39.534219],
            [-119.789094, 39.534789],
            [-119.789057, 39.535102],
            [-119.789699, 39.535547],
            [-119.790124, 39.535791],
            [-119.790855, 39.536223],
            [-119.791645, 39.536439],
            [-119.792992, 39.536485],
            [-119.793527, 39.536478],
            [-119.79358, 39.535763],
            [-119.793395, 39.534547],
            [-119.793372, 39.534397],
            [-119.792931, 39.534381],
            [-119.792933, 39.534141],
            [-119.792265, 39.534167],
            [-119.791178, 39.53418],
            [-119.790793, 39.534175],
            [-119.790799, 39.533857],
            [-119.790359, 39.533861],
            [-119.790148, 39.533844],
            [-119.790074, 39.533844],
            [-119.790028, 39.533832]
          ]
        ]
      },
      "properties": {
        "name": "Polygon"
      }
    }
  ]
}
